MANIFEST.in
README
setup.py
yayson.py
./__init__.py
./yayson.py
yayson.egg-info/PKG-INFO
yayson.egg-info/SOURCES.txt
yayson.egg-info/dependency_links.txt
yayson.egg-info/not-zip-safe
yayson.egg-info/requires.txt
yayson.egg-info/top_level.txt