Metadata-Version: 1.1
Name: yayson
Version: 0.3.1
Summary: Get colorized and indented JSON in the terminal
Home-page: http://sebdah.github.com/yayson/
Author: Sebastian Dahlgren
Author-email: sebastian.dahlgren@gmail.com
License: Apache License, Version 2.0
Keywords: color colorized json indented beautiful pretty
Platform: Any
Classifier: Development Status :: 4 - Beta
Classifier: Environment :: Console
Classifier: License :: OSI Approved :: Apache Software License
Classifier: Operating System :: OS Independent
Classifier: Programming Language :: Python
